{"elapsed":"1.001","endpoint-url":"https://www.great-yarmouth.gov.uk/CHttpHandler.ashx?id=4930&p=0","entry-date":"2022-02-27T00:17:08.012055","request-headers":{"Accept":"*/*","Accept-Encoding":"gzip, deflate","Connection":"keep-alive","User-Agent":"DLUHC Digital Land"},"response-headers":{"Cache-Control":"no-cache, no-store","Content-Length":"16633","Content-Type":"text/html; charset=utf-8","Date":"Sun, 27 Feb 2022 00:22:07 GMT","Expires":"-1","Pragma":"no-cache","Server":"Microsoft-IIS/8.5","Set-Cookie":"ASP.NET_SessionId=0522rudarnloijvxxujf4esf; path=/; HttpOnly; SameSite=Lax, clientvars=27550699-ea13-41b0-8d39-345a1fa56a2e; path=/; HttpOnly, TextOnlyX=; expires=Mon, 27-Feb-2017 00:22:07 GMT; path=/, mode=0; expires=Sun, 05-Jun-2022 23:22:07 GMT; path=/","X-Powered-By":"ASP.NET"},"ssl-verify":true,"status":"404"}