{"bytes":3282,"elapsed":"0.495","endpoint-url":"http://www.queenelizabetholympicpark.co.uk/-/media/lldc/planning/brownfield-register/lldc-brownfield-register-csv-web-version.ashx?la=en","entry-date":"2022-02-27T00:17:08.012055","request-headers":{"Accept":"*/*","Accept-Encoding":"gzip, deflate","Connection":"keep-alive","User-Agent":"DLUHC Digital Land"},"resource":"40ba241c5f5da1de68d3c025e68210d8707413a4d7c50ce9396a006802556669","response-headers":{"Accept-Ranges":"bytes","CF-Cache-Status":"MISS","CF-RAY":"6e3d4d49ef6c82d4-IAD","Cache-Control":"private, max-age=604800","Connection":"keep-alive","Content-Disposition":"attachment; filename=\"LLDC Brownfield Register csv Web Version.csv\"","Content-Length":"3282","Content-Type":"application/octet-stream","Date":"Sun, 27 Feb 2022 00:29:59 GMT","Expect-CT":"max-age=604800, report-uri=\"https://report-uri.cloudflare.com/cdn-cgi/beacon/expect-ct\"","Expires":"Sun, 06 Mar 2022 00:29:58 GMT","Last-Modified":"Wed, 20 Dec 2017 10:14:35 GMT","NEL":"{\"success_fraction\":0,\"report_to\":\"cf-nel\",\"max_age\":604800}","Report-To":"{\"endpoints\":[{\"url\":\"https:\\/\\/a.nel.cloudflare.com\\/report\\/v3?s=q3CH8E3M%2BfoefL1lCq6io%2BFlwD7YRTwFhMM17RiN1fjOCAX2MZOWPWHYAKI7mhVOo03pvHJg10dPCHOCn9tAuqXbPutmv9dy9WshJ0Vayn9Whg3EVLmXnu3U4u7ohmhALnQo1WEhlw49twKSWI49QUf3QMni\"}],\"group\":\"cf-nel\",\"max_age\":604800}","Server":"cloudflare","Vary":"Accept-Encoding"},"ssl-verify":true,"status":"200"}