{"elapsed":"1.418","endpoint-url":"https://www.dudley.gov.uk/media/14362/brownfield-land.csv","entry-date":"2022-02-27T00:17:08.012055","request-headers":{"Accept":"*/*","Accept-Encoding":"gzip, deflate","Connection":"keep-alive","Cookie":"TS015c65a0=0104e7c0624618403e2a4cac43e7e8e95907de99ce3524d9fec5003ac0ea90de328d1200878828a51d1098c5069ad2ee6b85997827","User-Agent":"DLUHC Digital Land"},"resource":"c511f35079bcfba97b319b469a351bf49e5199693e886bffd79aad1725556982","response-headers":{"Accept-Ranges":"bytes","Content-Length":"48716","Content-Type":"application/octet-stream","Date":"Sun, 27 Feb 2022 00:44:20 GMT","ETag":"\"41aa6da8aee6d71:0\"","Last-Modified":"Wed, 01 Dec 2021 12:26:25 GMT","Set-Cookie":"TS015c65a0=0104e7c0629342e0b56a474cf1e4fc620dc4ee98b37302cdc4de7c83d0d97c680ca32e3de21636d3970144263f4de0c7a01189da2c; Path=/; Domain=.www.dudley.gov.uk; Secure; HTTPOnly"},"ssl-verify":true,"status":"200"}