{"elapsed":"3.391","endpoint-url":"https://www.gravesham.gov.uk/__data/assets/excel_doc/0009/449568/Gravesham_BrownfieldLandRegister.xlsm","entry-date":"2021-03-13T00:12:20.226306","request-headers":{"Accept":"*/*","Accept-Encoding":"gzip, deflate","Connection":"keep-alive","User-Agent":"Digital Land"},"response-headers":{"Cache-Control":"max-age=86400, s-maxage=86400, public","Connection":"close","Content-Encoding":"gzip","Content-Length":"6179","Content-Type":"text/html; charset=utf-8","Date":"Sat, 13 Mar 2021 00:27:27 GMT","Expires":"Sun, 14 Mar 2021 00:27:28 GMT","Pragma":"cache","Server":"Apache","Set-Cookie":"SQ_SYSTEM_SESSION=948kk2njkg0mig1d49a7qo84e737j6d9vsk7tk64tvo0hcla4gfgauogok8h9pftovjl4nh863oc9r5a7nc37huo90s5mck3c8qqhd1; path=/; secure; HttpOnly, csrf=a6ec4d22c66c3115c43d97dd45e90419e7374ef0; path=/; domain=.tmbc.gov.uk; secure; HttpOnly","Strict-Transport-Security":"max-age=31536000; includeSubDomains","Vary":"Accept-Encoding","X-Content-Type-Options":"nosniff","X-Frame-Options":"SAMEORIGIN"},"ssl-verify":true,"status":"404"}