{"elapsed":"0.623","endpoint-url":"https://www.copeland.gov.uk/sites/default/files/attachments/copeland_brownfield_register.csv","entry-date":"2021-01-05T00:23:41.861054","request-headers":{"Accept":"*/*","Accept-Encoding":"gzip, deflate","Connection":"keep-alive","User-Agent":"Digital Land"},"response-headers":{"Accept-Ranges":"bytes","Age":"0","Cache-Control":"public, max-age=10800","Connection":"keep-alive","Content-Encoding":"gzip","Content-Language":"en","Content-Length":"6531","Content-Type":"text/html; charset=utf-8","Date":"Tue, 05 Jan 2021 00:36:44 GMT","Etag":"\"1609807004-1\"","Expires":"Sun, 19 Nov 1978 05:00:00 GMT","Last-Modified":"Tue, 05 Jan 2021 00:36:44 GMT","Server":"nginx","Vary":"Cookie,Accept-Encoding","Via":"1.1 varnish","X-Content-Type-Options":"nosniff","X-Drupal-Cache":"MISS","X-Frame-Options":"SAMEORIGIN","X-Varnish":"1399134244","X-Varnish-Backend":"vm77_10","X-Varnish-Cache":"MISS","X-Varnish-Cacheable":"NO (4xx)","X-Varnish-Host":"vm83-23"},"ssl-verify":true,"status":"404"}