{"elapsed":"14.652","endpoint-url":"https://info.westberks.gov.uk/CHttpHandler.ashx?id=46724&p=0","entry-date":"2024-02-09T00:20:41.886492","request-headers":{"Accept":"*/*","Accept-Encoding":"gzip, deflate","Connection":"keep-alive","User-Agent":"DLUHC Digital Land"},"response-headers":{"Cache-Control":"private","Content-Encoding":"gzip","Content-Length":"3120","Content-Type":"text/html; charset=utf-8","Date":"Fri, 09 Feb 2024 00:47:23 GMT","Server":"Microsoft-IIS/10.0","Set-Cookie":"ASP.NET_SessionId=kfna3j53fzoetqnwxxy35p4f; path=/; HttpOnly; SameSite=Lax","Vary":"Accept-Encoding","X-Powered-By":"ASP.NET"},"ssl-verify":true,"status":"200"}