{"elapsed":"1.242","endpoint-url":"https://info.westberks.gov.uk/CHttpHandler.ashx?id=46724&p=0","entry-date":"2021-11-21T00:29:51.277423","request-headers":{"Accept":"*/*","Accept-Encoding":"gzip, deflate","Connection":"keep-alive","User-Agent":"Digital Land"},"resource":"47ae15c373da005ad5d1280e13163dca5725ed4a04b32374991d14004b9eab78","response-headers":{"Cache-Control":"private","Content-Disposition":"filename=\"2018_Part_1_Brownfield_Land_Register.csv\"","Content-Length":"40679","Content-Type":"application/vnd.ms-excel","Date":"Sun, 21 Nov 2021 00:38:32 GMT","Server":"Microsoft-IIS/10.0","Set-Cookie":"clientvars=aee289be-68f8-41a9-a9c3-052fade2a819; path=/; HttpOnly","X-Powered-By":"ASP.NET"},"ssl-verify":true,"status":"200"}