{"elapsed":"0.848","endpoint-url":"https://www.broads-authority.gov.uk/__data/assets/text_file/0028/256681/broads_authority_brownfieldregister_2019_12_04.csv","entry-date":"2021-09-28T00:26:59.990541","request-headers":{"Accept":"*/*","Accept-Encoding":"gzip, deflate","Connection":"keep-alive","User-Agent":"Digital Land"},"response-headers":{"Cache-Control":"private, max-age=0","Connection":"keep-alive","Content-Encoding":"gzip","Content-Type":"text/html; charset=utf-8","Date":"Tue, 28 Sep 2021 00:27:21 GMT","Expires":"Tue, 28 Sep 2021 00:57:20 GMT","Pragma":"cache","Server":"openresty","Set-Cookie":"SQ_SYSTEM_SESSION=cbhuhi3shvvgbploi7cfmbo212i19a3foufs74t9m1nrs8gqeuujo8gcmsk89p1u94afvv0jht026dvd5u7bu3v53jusoic4puvgsm1; path=/; secure; HttpOnly","Transfer-Encoding":"chunked","Vary":"Accept-Encoding, Accept-Encoding","Via":"1.1 np-web01.ash2.squiz.cloud","X-Cache":"MISS from np-web01.ash2.squiz.cloud","X-Content-Type-Options":"nosniff","X-Frame-Options":"SAMEORIGIN","X-Request-ID":"2239a919-a3ba-4c91-9c6e-b51689e98620","X-upgrade-enabled":"off"},"ssl-verify":true,"status":"404"}