{"elapsed":"0.167","endpoint-url":"https://www.sefton.gov.uk/media/1504440/Brownfield-Land-Register-2018-Final.csv","entry-date":"2021-09-16T09:55:47.724630","request-headers":{"Accept":"*/*","Accept-Encoding":"gzip, deflate","Connection":"keep-alive","User-Agent":"Digital Land"},"response-headers":{"CF-Cache-Status":"EXPIRED","CF-Ray":"68f941c97af56598-LHR","Cache-Control":"private","Connection":"keep-alive","Content-Encoding":"gzip","Content-Type":"text/html","Date":"Thu, 16 Sep 2021 10:02:03 GMT","Expect-CT":"max-age=604800, report-uri=\"https://report-uri.cloudflare.com/cdn-cgi/beacon/expect-ct\"","Server":"cloudflare","Transfer-Encoding":"chunked","Vary":"Accept-Encoding"},"ssl-verify":true,"status":"404"}