{"elapsed":"2.243","endpoint-url":"https://www.canterbury.gov.uk/download/downloads/id/1217/canterbury_brownfield_land_register.csv","entry-date":"2021-11-25T00:29:39.136173","request-headers":{"Accept":"*/*","Accept-Encoding":"gzip, deflate","Connection":"keep-alive","User-Agent":"Digital Land"},"response-headers":{"Accept-Ranges":"bytes","Cache-Control":"no-store","Connection":"keep-alive","Content-Length":"41758","Content-Type":"text/html; charset=utf-8","Date":"Thu, 25 Nov 2021 00:41:36 GMT","ETag":"\"8524b579358b43c23d338d5a87540940\"","Last-Modified":"Wed, 24 Nov 2021 16:43:17 GMT","Pragma":"no-cache","Referrer-Policy":"same-origin","Server":"AmazonS3","Strict-Transport-Security":"max-age=63072000; includeSubdomains; preload","Via":"1.1 6396e88c437c096ef98930ce29f731a3.cloudfront.net (CloudFront)","X-Amz-Cf-Id":"OcIPpCj7t4JhWqj4HmeAp74dizJx30pylTjzveK0vSft0CIWjK105g==","X-Amz-Cf-Pop":"SEA73-P1","X-Cache":"Error from cloudfront","X-Content-Type-Options":"nosniff","X-Frame-Options":"DENY","X-XSS-Protection":"1; mode=block","x-amz-id-2":"LdBDpxxnkzi7YniGRiMbdbuNQMy47bW1mL4qdjc88YBjvc5DSpoFDXN3AdrPPLrPRljh2GtS4z0=","x-amz-request-id":"FZW0TJKXJHSSNWE4","x-amz-version-id":"null"},"ssl-verify":true,"status":"404"}