{"elapsed":"0.745","endpoint-url":"https://s3.eu-west-2.amazonaws.com/digital-land/brownfield-sites/redbridge-brownfield-land-register.csv","entry-date":"2022-04-24T00:16:15.636538","request-headers":{"Accept":"*/*","Accept-Encoding":"gzip, deflate","Connection":"keep-alive","User-Agent":"DLUHC Digital Land"},"resource":"30a93d60a53723e9bf458f74f45675bcdef1eb4dcc80ca195188fc2d68fe7e16","response-headers":{"Accept-Ranges":"bytes","Content-Length":"136964","Content-Type":"text/csv","Date":"Sun, 24 Apr 2022 00:24:36 GMT","ETag":"\"fbff0d035337b08d879931cf7e67a37a\"","Last-Modified":"Tue, 31 Jul 2018 15:56:16 GMT","Server":"AmazonS3","x-amz-id-2":"NxAC8xUWNvUKNK4mtMyEmvazAhYNB4s4uq/UAmkZRItb2CUQ+mXbfz49QxlmFh0PqVzqc6vODog=","x-amz-request-id":"T46JYD16PX6HWMW8"},"ssl-verify":true,"status":"200"}