{"elapsed":"0.926","endpoint-url":"https://www.walthamforest.gov.uk/node/4007","entry-date":"2022-05-29T00:19:17.804187","request-headers":{"Accept":"*/*","Accept-Encoding":"gzip, deflate","Connection":"keep-alive","User-Agent":"DLUHC Digital Land"},"response-headers":{"Cache-Control":"max-age=1800, public","Connection":"keep-alive","Content-Encoding":"gzip","Content-Length":"9883","Content-Type":"text/html; charset=UTF-8","Content-language":"en","Date":"Sat, 28 May 2022 00:22:39 GMT","ETag":"W/\"1653783812\"","Expires":"Sun, 19 Nov 1978 05:00:00 GMT","Last-Modified":"Sun, 29 May 2022 00:23:32 GMT","Link":"<https://www.walthamforest.gov.uk/404-page-not-found>; rel=\"canonical\", <https://www.walthamforest.gov.uk/node/4007>; rel=\"shortlink\", <https://www.walthamforest.gov.uk/404-page-not-found>; rel=\"canonical\", <https://www.walthamforest.gov.uk/node/4007>; rel=\"shortlink\"","Permissions-Policy":"interest-cohort=()","Server":"nginx","Strict-Transport-Security":"max-age=31536000; includeSubDomains","Vary":"Cookie","Via":"1.1 fe837f35c008063fe28d7f6bd9b1c62a.cloudfront.net (CloudFront)","X-Amz-Cf-Id":"bsbwP1-bdDWuH2B5xSZ103cn51R-30c4ZJWdJ7Zz9P3Jl7cBkJCs2A==","X-Amz-Cf-Pop":"LAX3-C4","X-Cache":"Error from cloudfront","X-Content-Type-Options":"nosniff","X-Drupal-Cache":"MISS","X-Drupal-Dynamic-Cache":"HIT","X-Frame-Options":"SAMEORIGIN","X-Generator":"Drupal 9 (https://www.drupal.org)","X-UA-Compatible":"IE=edge"},"ssl-verify":true,"status":"404"}