{"elapsed":"0.167","endpoint-url":"https://www.threerivers.gov.uk/download?id=43813","entry-date":"2024-02-08T00:19:24.259434","request-headers":{"Accept":"*/*","Accept-Encoding":"gzip, deflate","Connection":"keep-alive","User-Agent":"DLUHC Digital Land"},"response-headers":{"Connection":"keep-alive","Content-Length":"919","Content-Type":"text/html","Date":"Thu, 08 Feb 2024 00:46:06 GMT","Server":"CloudFront","Via":"1.1 03c28758fe0abb70088fb45c6855d854.cloudfront.net (CloudFront)","X-Amz-Cf-Id":"hjymnfilHtAcHwVHKaQZoKtIDMO_0D_CaxTCygMH5AK7kJ6Tne1Zig==","X-Amz-Cf-Pop":"IAD61-P2","X-Cache":"Error from cloudfront"},"ssl-verify":true,"status":"403"}