{"elapsed":"1.482","endpoint-url":"https://chorley.gov.uk/media/863/brownfield-sites-Chorley-2020/Excel/brownfield-sites_Chorley_December_2020.csv?m=637478600111400000","entry-date":"2023-01-23T00:17:19.008453","request-headers":{"Accept":"*/*","Accept-Encoding":"gzip, deflate","Connection":"keep-alive","User-Agent":"DLUHC Digital Land"},"response-headers":{"Cache-Control":"no-cache, no-store","Content-Length":"28811","Content-Type":"text/html; charset=utf-8","Date":"Mon, 23 Jan 2023 01:12:08 GMT","Expires":"-1","Pragma":"no-cache","Server":"","Strict-Transport-Security":"max-age=25920000","X-Content-Type-Options":"nosniff","X-Frame-Options":"SAMEORIGIN","X-Powered-By":"","X-UA-Compatible":"IE=Edge","X-XSS-Protection":"1; mode=block"},"ssl-verify":true,"status":"404"}