{"elapsed":"0.587","endpoint-url":"https://www.queenelizabetholympicpark.co.uk/-/media/lldc/planning/brownfield-register/lldc-brownfield-register-csv-web-version.ashx?la=en","entry-date":"2021-03-28T00:07:19.500710","request-headers":{"Accept":"*/*","Accept-Encoding":"gzip, deflate","Connection":"keep-alive","Cookie":"__cfduid=d52fb4ff5e68575af819dd4beb6589e9a1616890232","User-Agent":"Digital Land"},"resource":"40ba241c5f5da1de68d3c025e68210d8707413a4d7c50ce9396a006802556669","response-headers":{"Accept-Ranges":"bytes","CF-Cache-Status":"REVALIDATED","CF-RAY":"636cac1e5dabcf04-IAD","Cache-Control":"private, max-age=604800","Connection":"keep-alive","Content-Disposition":"attachment; filename=\"LLDC Brownfield Register csv Web Version.csv\"","Content-Length":"3282","Content-Type":"application/octet-stream","Date":"Sun, 28 Mar 2021 00:16:53 GMT","Expect-CT":"max-age=604800, report-uri=\"https://report-uri.cloudflare.com/cdn-cgi/beacon/expect-ct\"","Expires":"Sun, 04 Apr 2021 00:16:53 GMT","Last-Modified":"Wed, 20 Dec 2017 10:14:35 GMT","NEL":"{\"max_age\":604800,\"report_to\":\"cf-nel\"}","Report-To":"{\"endpoints\":[{\"url\":\"https:\\/\\/a.nel.cloudflare.com\\/report?s=nw0LjO1Z3r24vZGiFkDcQEyRZVss90IB6S%2FijyIgWr2M8l3QCXJjH5gep%2B5a6U4t52BUuxIeyJtFWtv%2FW9kI0RMmp1Zbr3NmvUP10T%2FRUytH4daQ8LUVdCMO6DHVE1fCyT6hfg%3D%3D\"}],\"group\":\"cf-nel\",\"max_age\":604800}","Server":"cloudflare","Vary":"Accept-Encoding","cf-request-id":"0917c9e6f50000cf04739c4000000001"},"ssl-verify":true,"status":"200"}