{"elapsed":"1.232","endpoint-url":"https://www.croydon.gov.uk/sites/default/files/2021-01/Brownfield%20_register_2020.xlsx","entry-date":"2023-10-16T00:19:01.226757","request-headers":{"Accept":"*/*","Accept-Encoding":"gzip, deflate","Connection":"keep-alive","User-Agent":"DLUHC Digital Land"},"resource":"c1a105b25b85f2ea73a8653fd3e4eac3262cc217a0452a386b6bc9d44c24ae3e","response-headers":{"Accept-Ranges":"bytes","Cache-Control":"max-age=31536000","Content-Length":"49137","Content-Type":"application/vnd.openxmlformats-officedocument.spreadsheetml.sheet","Date":"Mon, 16 Oct 2023 01:20:28 GMT","ETag":"\"bff1-5b812b5e91038\"","Expires":"Tue, 15 Oct 2024 01:20:28 GMT","Last-Modified":"Mon, 04 Jan 2021 13:03:04 GMT","X-Azure-Ref":"03I8sZQAAAAB991BnGz+QRJo992mzy2twU0pDMjExMDUxMjAyMDM5ADZiMGM0Yjc4LWNiMTUtNDllMC1hNDVlLWIzNjQwNjFiMjcxMg==","X-Azure-Ref-OriginShield":"03I8sZQAAAABbaUTLJjiwSIBm2TOlvNFGU0pDMjExMDUxMjA3MDUzADZiMGM0Yjc4LWNiMTUtNDllMC1hNDVlLWIzNjQwNjFiMjcxMg==","X-Cache":"TCP_MISS","X-Content-Type-Options":"nosniff"},"ssl-verify":true,"status":"200"}