{"elapsed":"0.675","endpoint-url":"https://www.cheltenham.gov.uk/downloads/file/7903/cheltenham_brownfield_register_2019","entry-date":"2023-08-24T00:17:15.671283","request-headers":{"Accept":"*/*","Accept-Encoding":"gzip, deflate","Connection":"keep-alive","Cookie":"TestCookie=Test; PHPSESSID=ywgC9hpq2ntcdQq1a-XHgBNd3WxLxuX8OJ4GuORF3A1fU5DQ3jXQ1Fd727f%2Cb6T0","User-Agent":"DLUHC Digital Land"},"response-headers":{"Cache-Control":"no-store, no-cache, must-revalidate","Connection":"keep-alive","Content-Encoding":"gzip","Content-Length":"4822","Content-Type":"text/html; charset=UTF-8","Date":"Thu, 24 Aug 2023 01:24:03 GMT","Expires":"Thu, 19 Nov 1981 08:52:00 GMT","Node":"jadu-web-1","Pragma":"no-cache","Server":"Web Server","Set-Cookie":"PHPSESSID=XEOTgKpX93xhoS6N6tBJABp%2CZLZ11yjZUrup047YaU5Ywlb2NuOynUaYahxYTr8i; path=/; secure; HttpOnly, TestCookie=Test; path=/; domain=www.cheltenham.gov.uk; HttpOnly","Strict-Transport-Security":"max-age=2592000","Vary":"Accept-Encoding","X-Content-Type-Options":"nosniff","X-Frame-Options":"SAMEORIGIN","X-UA-Compatible":"IE=edge,chrome=1","X-XSS-Protection":"1; mode=block"},"ssl-verify":true,"status":"200"}