{"elapsed":"1.046","endpoint-url":"https://walthamforest.gov.uk/node/5437","entry-date":"2020-07-10T00:29:03.091385","request-headers":{"Accept":"*/*","Accept-Encoding":"gzip, deflate","Connection":"keep-alive","Cookie":"SESS6662e7a308dd6c21d2dbdf87dadca3a3=InouCbwEYzkReLorbl1P2YkAv-vwSo09bjHPBkTLj1U; SSESS6662e7a308dd6c21d2dbdf87dadca3a3=_8neiAmbfm6gw8zGlRnzRPSyb-D85C2uslty-WJ3AWM; device=3; device_type=0","User-Agent":"Digital Land data collector"},"resource":"3089a3f8e06e4b03f30955c91ee33ec80dd979c6ff48e9be59a414fe244e71a5","response-headers":{"Accept-Ranges":"bytes, bytes","Age":"0","Cache-Control":"max-age=1209600","Connection":"keep-alive","Content-Length":"72788","Content-Type":"text/csv","Date":"Fri, 10 Jul 2020 00:37:44 GMT","ETag":"\"11c54-57d899a2473a8\"","Expires":"Fri, 24 Jul 2020 00:37:44 GMT","Last-Modified":"Fri, 21 Dec 2018 15:07:13 GMT","Server":"Apache","Via":"1.1 varnish-v4","X-Content-Type-Options":"nosniff","X-Varnish":"1680874"},"status":"200"}