{"elapsed":"2.256","endpoint-url":"https://dataworks.calderdale.gov.uk/download/brownfield-land-register/ce479c95-8ad9-4e3f-98fe-c8c59d0a7742/Brownfield%20land%20register%202018.xlsx","entry-date":"2023-01-14T00:17:33.249867","request-headers":{"Accept":"*/*","Accept-Encoding":"gzip, deflate","Connection":"keep-alive","User-Agent":"DLUHC Digital Land"},"resource":"c9a55b734c7c65307e2341ff1bee5b70f7c16ccdf89a5c2ec35814f65c33ae1a","response-headers":{"Access-Control-Allow-Origin":"*","CF-Cache-Status":"MISS","CF-RAY":"789246dace36aa4c-DFW","Cache-Control":"max-age=14400","Connection":"keep-alive","Content-Disposition":"attachment","Content-Encoding":"gzip","Content-Type":"text/csv; charset=utf-8","Date":"Sat, 14 Jan 2023 00:32:51 GMT","Etag":"\"a0f9c7cabc733983c7d9218dc57e56eb\"","Last-Modified":"Thu Jun 16 2022 18:00:48 GMT+0000 (Coordinated Universal Time)","NEL":"{\"success_fraction\":0,\"report_to\":\"cf-nel\",\"max_age\":604800}","Report-To":"{\"endpoints\":[{\"url\":\"https:\\/\\/a.nel.cloudflare.com\\/report\\/v3?s=GqJyQ0lNX%2Fa%2Ffv1rcW9%2BtPD2oQTztmBFNUN%2Fj1vLRU29ZbQ%2FrGuIw9uS%2BB632Rq600xrYmZJXykKFFJyJST65PyjTddZAouE1rZsQ9vM0m1bEjwmN%2BsNRDLSf6%2Btw3G4Xth9Y%2BMA2q1rCCc84g%3D%3D\"}],\"group\":\"cf-nel\",\"max_age\":604800}","Server":"cloudflare","Transfer-Encoding":"chunked","Vary":"Accept-Encoding","Via":"1.1 vegur, 1.1 vegur"},"ssl-verify":true,"status":"200"}