{"elapsed":"1.139","endpoint-url":"https://www.woking2027.info/ldfregisters/brownfieldlandregistercsv.csv","entry-date":"2023-10-23T00:19:15.198536","request-headers":{"Accept":"*/*","Accept-Encoding":"gzip, deflate","Connection":"keep-alive","User-Agent":"DLUHC Digital Land"},"resource":"0926985544238c3b43555433cadeb840b5aa422503870e724fd52c87267b08b3","response-headers":{"Accept-Ranges":"bytes","CF-Cache-Status":"EXPIRED","CF-RAY":"81a61172b87d172a-SJC","Cache-control":"max-age=14400","Connection":"keep-alive","Content-Length":"25993","Content-Type":"application/octet-stream","Date":"Mon, 23 Oct 2023 01:04:49 GMT","Expires":"Mon, 23 Oct 2023 01:04:49 GMT","Last-Modified":"Sun, 22 Oct 2023 01:05:43 GMT","NEL":"{\"success_fraction\":0,\"report_to\":\"cf-nel\",\"max_age\":604800}","Pragma":"no-cache","Referrer-Policy":"no-referrer-when-downgrade","Report-To":"{\"endpoints\":[{\"url\":\"https:\\/\\/a.nel.cloudflare.com\\/report\\/v3?s=MG444JHU25zbhKs1XEVRd91wfq2TMEL1BTg7RBvia7Po1NgIyDsXHs8849b0BRbvm6Z50lYF3DuPADNSXureifvqPW%2B9SNB%2BfXDp%2BygI8qXZmYs1JkAQAAm6faLWuMnc6i3mZvkt\"}],\"group\":\"cf-nel\",\"max_age\":604800}","Server":"cloudflare","Vary":"Accept-Encoding","X-Content-Type-Options":"nosniff","X-XSS-Protection":"1; mode=block","alt-svc":"h3=\":443\"; ma=86400"},"ssl-verify":true,"status":"200"}