{"elapsed":"1.949","endpoint-url":"https://www.birmingham.gov.uk/download/downloads/id/9037/brownfield_register.csv","entry-date":"2022-06-03T00:16:42.249971","request-headers":{"Accept":"*/*","Accept-Encoding":"gzip, deflate","Connection":"keep-alive","User-Agent":"DLUHC Digital Land"},"resource":"4a083bf202de3408bc048f88da2a4cdf1657d70ec543c386859f6f6646f2ff76","response-headers":{"Cache-Control":"must-revalidate, post-check=0, pre-check=0","Connection":"Keep-Alive","Content-Disposition":"attachment; filename=\"Brownfield_Register_2020__AF_.csv\"","Content-Length":"319219","Content-Type":"application/vnd.ms-excel","Date":"Fri, 03 Jun 2022 00:20:22 GMT","Expires":"Sat, 26 Jul 1997 05:00:00 GMT","Keep-Alive":"timeout=5, max=100","Pragma":"public","Set-Cookie":"m6jA1MEzDRPHIVj5=cfafba60e6538cfe8ee25a935dd6349a; path=/; secure; HttpOnly; HttpOnly;SameSite=None; Secure, TestCookie=Test; path=/; domain=www.birmingham.gov.uk; secure; HttpOnly; HttpOnly;SameSite=None; Secure, TS01fe61fd=01fd5b8c7b07cadf1e0c92b9d4e6cc7ee92eb01d73ebdeec9af556c93e4cda8aff02f3faa7351182e6c73a426420d10bdfbd96867efd148620cb71ede0d4804d5352a2dfd1; Path=/; Secure; HTTPOnly, TS01be1219=01fd5b8c7ba0f88b7856c3017c6ff60e2c6f1be14febdeec9af556c93e4cda8aff02f3faa74f719f4407274db602b60122f9e7163bc36cb8bca67dcafb0595e30318195e81; path=/; domain=www.birmingham.gov.uk; HTTPonly; Secure","Strict-Transport-Security":"max-age=2592000","Vary":"Host","Via":"1.1 sjc1-bit12028","X-Content-Type-Options":"nosniff","X-Frame-Options":"SAMEORIGIN","X-XSS-Protection":"1; mode=block"},"ssl-verify":true,"status":"200"}