{"elapsed":"1.17","endpoint-url":"https://www.canterbury.gov.uk/download/downloads/id/1402/canterbury_brownfield_land_register.csv","entry-date":"2021-08-30T00:26:26.922652","request-headers":{"Accept":"*/*","Accept-Encoding":"gzip, deflate","Connection":"keep-alive","User-Agent":"Digital Land"},"response-headers":{"Accept-Ranges":"bytes","Cache-Control":"no-store","Connection":"keep-alive","Content-Length":"23876","Content-Type":"text/html; charset=utf-8","Date":"Mon, 30 Aug 2021 00:59:21 GMT","ETag":"\"f9c0f18033e1b6d2ac9710be879379b5\"","Last-Modified":"Sun, 29 Aug 2021 15:58:00 GMT","Pragma":"no-cache","Referrer-Policy":"same-origin","Server":"AmazonS3","Strict-Transport-Security":"max-age=63072000; includeSubdomains; preload","Via":"1.1 9cdf83ac92372e14c2c11c5760f6d17a.cloudfront.net (CloudFront)","X-Amz-Cf-Id":"IVYSlTLwlu9Lv3DLMvs2P9nb_7vO_wWyq17wFHGJ7sbsi2pCrgeckA==","X-Amz-Cf-Pop":"IAD79-C3","X-Cache":"Error from cloudfront","X-Content-Type-Options":"nosniff","X-Frame-Options":"DENY","X-XSS-Protection":"1; mode=block","x-amz-id-2":"iPgwIj86gFi7AQERZBVfDvnYofOqswbmXN4S3Ubiiq4xtgYpmqdduI8Thf3oDvYm2/VqmNRWlec=","x-amz-request-id":"9JMC2Y8N1B0SRA3P","x-amz-version-id":"cf2IpwuHkryRusg1EeHG3xjt6xRnLfMI"},"ssl-verify":true,"status":"404"}