{"elapsed":"1.616","endpoint-url":"http://www.brentwood.gov.uk/pdf/29122017084910000000.xlsm","entry-date":"2022-02-12T01:05:02.875588","request-headers":{"Accept":"*/*","Accept-Encoding":"gzip, deflate","Connection":"keep-alive","User-Agent":"DLUHC Digital Land"},"response-headers":{"Cache-Control":"no-cache, no-store, must-revalidate, private, private, no-cache, no-store, must-revalidate","Connection":"keep-alive","Content-Length":"60740","Content-Type":"text/html;charset=UTF-8","Date":"Sat, 12 Feb 2022 01:23:40 GMT","Expires":"Wed, 31 Dec 1969 16:00:00 PST","Pragma":"no-cache, no-cache","Referrer-Policy":"strict-origin-when-cross-origin","Server":"Placecube","Set-Cookie":"JSESSIONID=810B227342AB4CB31243562698571F87; Path=/; Secure; HttpOnly, COOKIE_SUPPORT=true; Max-Age=31536000; Expires=Sun, 12-Feb-2023 01:23:40 GMT; Path=/; Secure; HttpOnly, GUEST_LANGUAGE_ID=en_GB; Max-Age=31536000; Expires=Sun, 12-Feb-2023 01:23:40 GMT; Path=/; Secure; HttpOnly, AWSELB=51B35D8714C79A65B3BAFDB0A7D01651D35308276B4FA5B47BFDAB0DCE7831BB1571AC9855AF083E46320438CA1FC0145F0A9DEA708AC4DCA40F20895D7A831ED61A7A23B6F32668A9DD704816699059E37DBF1BD3;PATH=/;SECURE;HTTPONLY","Strict-Transport-Security":"max-age=31536000; includeSubdomains;","X-Content-Type-Options":"nosniff, nosniff","X-Frame-Options":"SAMEORIGIN","X-XSS-Protection":"1"},"ssl-verify":true,"status":"404"}