{"elapsed":"1.023","endpoint-url":"https://www.broads-authority.gov.uk/__data/assets/text_file/0028/256681/broads_authority_brownfieldregister_2019_12_04.csv","entry-date":"2023-03-07T00:21:53.285204","request-headers":{"Accept":"*/*","Accept-Encoding":"gzip, deflate","Connection":"keep-alive","User-Agent":"DLUHC Digital Land"},"response-headers":{"Cache-Control":"private, max-age=0","Connection":"keep-alive","Content-Encoding":"gzip","Content-Type":"text/html; charset=utf-8","Date":"Tue, 07 Mar 2023 01:10:15 GMT","Expires":"Tue, 07 Mar 2023 01:40:15 GMT","Pragma":"cache","Server":"openresty","Set-Cookie":"SQ_SYSTEM_SESSION=169780e0a1ce1358e405d38cf1445b8b; path=/; secure; HttpOnly","Transfer-Encoding":"chunked","Vary":"Accept-Encoding, Accept-Encoding","Via":"1.1 np2-web01.ash2.squiz.cloud","X-Cache":"MISS from np2-web01.ash2.squiz.cloud","X-Content-Type-Options":"nosniff","X-Frame-Options":"SAMEORIGIN","X-Request-ID":"8b250422-79c1-4ea6-b665-a32667c81296","X-upgrade-enabled":"off"},"ssl-verify":true,"status":"404"}