{"elapsed":"2.801","endpoint-url":"http://datashare.colchester.gov.uk/download/planning-and-licensing/brownfield-land-register/dec-2017/CSV","entry-date":"2023-12-25T00:24:25.919218","request-headers":{"Accept":"*/*","Accept-Encoding":"gzip, deflate","Connection":"keep-alive","Cookie":"Dynamics365PortalAnalytics=pfjyv4P23H6bJXC_dOqu4YbPZ9re4-vyTcuUVtROmOgJehIQYC83mQKRDJGy_HzQaTA4DU8QYqYSGj6j04L-Rh8SYKmEtqWjZh8dJ1V6f2JHwuKn44m5tdksE71DwFAjLovP7pH9nTT-nkeFpyl4gQ2; ARRAffinity=57d5258c349103c74d104ee6315d37036a8c6af8b0f5efa690b26d2a1fdd2129; ARRAffinitySameSite=57d5258c349103c74d104ee6315d37036a8c6af8b0f5efa690b26d2a1fdd2129","User-Agent":"DLUHC Digital Land"},"response-headers":{"Access-Control-Allow-Headers":"https://cbc-live-dotgovresources.azurewebsites.net/*","Access-Control-Allow-Methods":"GET, OPTIONS","Access-Control-Allow-Origin":"https://cbcliveb2c.b2clogin.com","Cache-Control":"no-cache, no-store, must-revalidate","Content-Encoding":"gzip","Content-Length":"24921","Content-Type":"text/html; charset=utf-8","Date":"Mon, 25 Dec 2023 00:54:28 GMT","Expires":"-1","Pragma":"no-cache","Server-Timing":"response-code; desc=200, correlationId; desc=fc611a5d-8afe-48cf-87e5-9b33851f2870","Set-Cookie":"ASP.NET_SessionId=02eim4tmmso02tl2mmxmit3p; path=/; secure; HttpOnly; SameSite=None","Strict-Transport-Security":"max-age=31536000; includeSubDomains; preload","Vary":"Accept-Encoding","X-Frame-Options":"SAMEORIGIN","x-ms-portal-app":"site-d40aeee5-a782-45ad-8f5a-540d634ba4ad-EUn","x-ms-request-id":"fc611a5d-8afe-48cf-87e5-9b33851f2870"},"ssl-verify":true,"status":"200"}