{"elapsed":"2.841","endpoint-url":"http://www.testvalley.gov.uk/assets/attach/5653/Test%20Valley%20Borough%20Council%20Brownfield%20Register.csv","entry-date":"2022-09-27T00:27:26.011930","request-headers":{"Accept":"*/*","Accept-Encoding":"gzip, deflate","Connection":"keep-alive","User-Agent":"DLUHC Digital Land"},"response-headers":{"Cache-Control":"private","Content-Length":"27645","Content-Type":"text/html; charset=utf-8","Date":"Tue, 27 Sep 2022 00:33:31 GMT","X-Powered-By":"ASP.NET"},"ssl-verify":true,"status":"404"}