{"elapsed":"0.409","endpoint-url":"http://woking2027.info/res/uploads/WokingBoroughCouncilBrownfieldLandRegister20171220.csv","entry-date":"2024-02-01T00:20:34.179629","request-headers":{"Accept":"*/*","Accept-Encoding":"gzip, deflate","Connection":"keep-alive","User-Agent":"DLUHC Digital Land"},"resource":"22da6ec5b4606f5e6ecb3870a934b09f3b84a98b24a6c9c163b6e0f7b2dcf788","response-headers":{"Accept-Ranges":"bytes","CF-Cache-Status":"HIT","CF-RAY":"84e6081b59af0ce3-LAX","Cache-Control":"public, max-age=315360000","Connection":"keep-alive","Content-Length":"68905","Content-Type":"application/octet-stream","Date":"Thu, 01 Feb 2024 00:20:58 GMT","ETag":"\"645bb3d1-10d29\"","Expires":"Thu, 31 Dec 2037 23:55:55 GMT","Last-Modified":"Wed, 10 May 2023 15:10:09 GMT","NEL":"{\"success_fraction\":0,\"report_to\":\"cf-nel\",\"max_age\":604800}","Report-To":"{\"endpoints\":[{\"url\":\"https:\\/\\/a.nel.cloudflare.com\\/report\\/v3?s=RkkPq5FMC0r50Vvj3TIIRqR6dQPs%2FTIqDb7uWW%2F5MsqhiJS21vlONx2ZilEwuzJEQx%2F3UuhYeOUv20RYhRHwwpPLPBUe6oOq%2FEZaN%2FkOT5kJoFuLuHlWBFNZYrKwy1EVDx3SZtDr\"}],\"group\":\"cf-nel\",\"max_age\":604800}","Server":"cloudflare","Vary":"Accept-Encoding","alt-svc":"h3=\":443\"; ma=86400"},"ssl-verify":true,"status":"200"}