{"elapsed":"1.874","endpoint-url":"https://www.northyorkmoors.org.uk/__data/assets/file/0019/145360/north-york-moors_brownfieldregister_2019-12-17_rev1.csv","entry-date":"2021-01-09T00:26:42.796317","request-headers":{"Accept":"*/*","Accept-Encoding":"gzip, deflate","Connection":"keep-alive","User-Agent":"Digital Land"},"response-headers":{"Cache-Control":"private, max-age=0","Connection":"keep-alive","Content-Encoding":"gzip","Content-Type":"text/html; charset=utf-8","Date":"Sat, 09 Jan 2021 00:29:05 GMT","Expires":"Sat, 09 Jan 2021 00:59:04 GMT","Pragma":"cache","Server":"openresty","Set-Cookie":"SQ_SYSTEM_SESSION=20veg7od47ob3siej7939jhvofcnliveonms7ovn0hvb2qkuno9c7ae7iim38nbeoc4ubma8fo21nokatlnef53gvh5ehecb69d2vf3; path=/; secure; HttpOnly","Transfer-Encoding":"chunked","Vary":"Accept-Encoding, Accept-Encoding","Via":"1.1 np-web01.ash2.squiz.cloud","X-Cache":"MISS from np-web01.ash2.squiz.cloud","X-Content-Type-Options":"nosniff","X-Frame-Options":"SAMEORIGIN","X-Request-ID":"5e15ca33-d4ca-4160-96c8-153512f468d1","X-upgrade-enabled":"off"},"ssl-verify":true,"status":"404"}