{"elapsed":"0.789","endpoint-url":"https://www.bournemouth.gov.uk/planningbuilding/PlanningPolicy/PlanningPolicyFiles/brownfieldlandregister/2018Register.csv","entry-date":"2021-08-06T00:24:38.511472","request-headers":{"Accept":"*/*","Accept-Encoding":"gzip, deflate","Connection":"keep-alive","User-Agent":"Digital Land"},"response-headers":{"connection":"close","content-length":"1290","content-type":"text/html; charset=utf-8","date":"Fri, 06 Aug 2021 00:55:07 GMT","referrer-policy":"strict-origin-when-cross-origin","strict-transport-security":"max-age=15768000","x-content-type-options":"nosniff","x-server-name":"z-bournemouth-CACHE1","x-varnish":"535250888","x-xss-protection":"1;mode=block"},"ssl-verify":false,"status":"404"}