{"elapsed":"0.557","endpoint-url":"http://www.queenelizabetholympicpark.co.uk/-/media/lldc/planning/brownfield-register/lldc-brownfield-register-csv-web-version.ashx?la=en","entry-date":"2020-10-03T00:45:41.265986","request-headers":{"Accept":"*/*","Accept-Encoding":"gzip, deflate","Connection":"keep-alive","User-Agent":"Digital Land data collector"},"resource":"40ba241c5f5da1de68d3c025e68210d8707413a4d7c50ce9396a006802556669","response-headers":{"Accept-Ranges":"bytes","CF-Cache-Status":"REVALIDATED","CF-RAY":"5dc2aecceead2605-IAD","Cache-Control":"private, max-age=604800","Connection":"keep-alive","Content-Disposition":"attachment; filename=\"LLDC Brownfield Register csv Web Version.csv\"","Content-Length":"3282","Content-Type":"application/octet-stream","Date":"Sat, 03 Oct 2020 00:52:51 GMT","Expect-CT":"max-age=604800, report-uri=\"https://report-uri.cloudflare.com/cdn-cgi/beacon/expect-ct\"","Expires":"Sat, 10 Oct 2020 00:52:51 GMT","Last-Modified":"Wed, 20 Dec 2017 10:14:35 GMT","Server":"cloudflare","Set-Cookie":"__cfduid=d0e0431d379aaa3c914e01392e2cbf51f1601686371; expires=Mon, 02-Nov-20 00:52:51 GMT; path=/; domain=.queenelizabetholympicpark.co.uk; HttpOnly; SameSite=Lax; Secure","Vary":"Accept-Encoding","cf-request-id":"058d8b9413000026056b1b7200000001"},"status":"200"}