{"elapsed":"0.984","endpoint-url":"https://new.enfield.gov.uk/services/planning/local-plan/planning-policy-information-enfield-blr-part-1.xlsx","entry-date":"2023-02-12T00:20:09.983237","request-headers":{"Accept":"*/*","Accept-Encoding":"gzip, deflate","Connection":"keep-alive","User-Agent":"DLUHC Digital Land"},"response-headers":{"Connection":"close","Content-Length":"56919","Content-Type":"text/html","Date":"Sun, 12 Feb 2023 00:42:06 GMT","Server":"","Strict-Transport-Security":"max-age=31536000; includeSubDomains","X-Frame-Options":"SAMEORIGIN","X-XSS-Protection":"1; mode=block"},"ssl-verify":true,"status":"502"}