{"elapsed":"0.742","endpoint-url":"http://www.fareham.gov.uk/PDF/planning/Brownfield/BrownfieldLandRegisterPart1.csv","entry-date":"2021-12-08T00:28:52.467694","request-headers":{"Accept":"*/*","Accept-Encoding":"gzip, deflate","Connection":"keep-alive","Cookie":"ApplicationGatewayAffinity=89b0f6b4e7076d0b5f212af4dacca7c9c6d38cf88bc60ba1d9330360f9deddcf; ApplicationGatewayAffinityCORS=89b0f6b4e7076d0b5f212af4dacca7c9c6d38cf88bc60ba1d9330360f9deddcf","User-Agent":"Digital Land"},"resource":"a80388011fb8b0aa02bf28128e765f3dcc71acab0798aa4570419e1e9f66d35b","response-headers":{"Accept-Ranges":"bytes","Content-Length":"23549","Content-Type":"application/octet-stream","Date":"Wed, 08 Dec 2021 01:11:06 GMT","ETag":"\"f357b842353d71:0\"","Last-Modified":"Thu, 27 May 2021 14:19:10 GMT","Server":"Microsoft-IIS/7.5","X-Powered-By":"ASP.NET"},"ssl-verify":true,"status":"200"}