{"elapsed":"15.819","endpoint-url":"https://www.luton.gov.uk/Environment/Lists/LutonDocuments/Excel/HOU-014.csv","entry-date":"2021-12-08T00:28:52.467694","request-headers":{"Accept":"*/*","Accept-Encoding":"gzip, deflate","Connection":"keep-alive","User-Agent":"Digital Land"},"response-headers":{"CF-RAY":"6ba207d0dcf456d4-IAD","Cache-Control":"private, max-age=0, no-store, no-cache, must-revalidate, post-check=0, pre-check=0","Connection":"keep-alive","Content-Type":"text/html; charset=UTF-8","Date":"Wed, 08 Dec 2021 00:56:06 GMT","Expires":"Thu, 01 Jan 1970 00:00:01 GMT","Referrer-Policy":"same-origin","Server":"cloudflare","Set-Cookie":"cf_ob_info=522:6ba207d0dcf456d4:IAD; path=/; expires=Wed, 08-Dec-21 00:56:36 GMT, cf_use_ob=443; path=/; expires=Wed, 08-Dec-21 00:56:36 GMT","Transfer-Encoding":"chunked","X-Frame-Options":"SAMEORIGIN"},"ssl-verify":true,"status":"522"}