{"elapsed":"0.992","endpoint-url":"https://middlesbrough.gov.uk/sites/default/files/Brownfield-sites-March-2019-update.csv","entry-date":"2020-07-24T00:31:32.676704","request-headers":{"Accept":"*/*","Accept-Encoding":"gzip, deflate","Connection":"keep-alive","Cookie":"AWSALB=DCrpnKEojiU+xDF+62a0oODgP+PJX2yCbzuPnpkhOeXgXrZvH/7X6xQRuxju/3ASynRNGJVk3/laY5dV1RC5U70uqxysPYCmGojaKFCh2F8j0XlCDSsae5o0CuJt; AWSALBCORS=DCrpnKEojiU+xDF+62a0oODgP+PJX2yCbzuPnpkhOeXgXrZvH/7X6xQRuxju/3ASynRNGJVk3/laY5dV1RC5U70uqxysPYCmGojaKFCh2F8j0XlCDSsae5o0CuJt","User-Agent":"Digital Land data collector"},"response-headers":{"Cache-Control":"no-cache, must-revalidate","Connection":"keep-alive","Content-Encoding":"gzip","Content-Language":"en","Content-Type":"text/html; charset=utf-8","Date":"Fri, 24 Jul 2020 00:41:21 GMT","Expires":"Sun, 19 Nov 1978 05:00:00 GMT","From-Origin":"same","Link":"<https://www.middlesbrough.gov.uk/>; rel=\"canonical\",<https://www.middlesbrough.gov.uk/>; rel=\"shortlink\"","Server":"nginx","Set-Cookie":"AWSALB=Vjk1qAoBO6Hxk7hKg5l2N/CBzO4CyndU7Trm8NfBnsFSOUnDRWUCjDh1Cy9NyxtiB042GQthophZNWufnrNR6kCBifMrnp8AhniSBMBvRbS6kjWawlhKifD5tDRW; Expires=Fri, 31 Jul 2020 00:41:20 GMT; Path=/, AWSALBCORS=Vjk1qAoBO6Hxk7hKg5l2N/CBzO4CyndU7Trm8NfBnsFSOUnDRWUCjDh1Cy9NyxtiB042GQthophZNWufnrNR6kCBifMrnp8AhniSBMBvRbS6kjWawlhKifD5tDRW; Expires=Fri, 31 Jul 2020 00:41:20 GMT; Path=/; SameSite=None; Secure, device=3; expires=Fri, 24-Jul-2020 02:41:20 GMT; Max-Age=7200; path=/; domain=.middlesbrough.gov.uk; secure; HttpOnly, device_type=0; expires=Fri, 24-Jul-2020 02:41:20 GMT; Max-Age=7200; path=/; domain=.middlesbrough.gov.uk; secure; HttpOnly","Strict-Transport-Security":"max-age=1000","Transfer-Encoding":"chunked","Vary":"Accept-Encoding","X-Content-Type-Options":"nosniff","X-Drupal-Cache":"MISS","X-Frame-Options":"SameOrigin","X-Generator":"Drupal 7 (http://drupal.org)","X-XSS-Protection":"1; mode=block"},"status":"404"}