{"elapsed":"2.907","endpoint-url":"http://datashare.colchester.gov.uk/download/planning-and-licensing/brownfield-land-register/dec-2017/CSV","entry-date":"2023-05-24T00:18:14.004378","request-headers":{"Accept":"*/*","Accept-Encoding":"gzip, deflate","Connection":"keep-alive","Cookie":"Dynamics365PortalAnalytics=_xcZeHFYBBdh3vMeABIBu5b4o_aMqEUgNPhp3-6LzbVFL6jTmr7Mc7RuVW0-EKID73pC41HIeHCflqMkpyV5N3nZtBLHYMqSWUM2IzS5Q52PlVMhY0eDu97gkw9A2LHemX0F37Pdg0gkWSC1m2-OTQ2; ARRAffinity=49c27ed01c22fa7ddd04f6543e7c9da6493ba1b81d655e1477ec83af4a1c6748; ARRAffinitySameSite=49c27ed01c22fa7ddd04f6543e7c9da6493ba1b81d655e1477ec83af4a1c6748","User-Agent":"DLUHC Digital Land"},"response-headers":{"Access-Control-Allow-Headers":"https://cbc-live-dotgovresources.azurewebsites.net/*","Access-Control-Allow-Methods":"GET, OPTIONS","Access-Control-Allow-Origin":"https://cbcliveb2c.b2clogin.com","Cache-Control":"no-cache, no-store, must-revalidate","Content-Encoding":"gzip","Content-Length":"23917","Content-Type":"text/html; charset=utf-8","Date":"Wed, 24 May 2023 00:56:49 GMT","Expires":"-1","Pragma":"no-cache","Set-Cookie":"ASP.NET_SessionId=1o4w1asktcpbon2du23klclu; path=/; secure; HttpOnly; SameSite=None","Strict-Transport-Security":"max-age=31536000; includeSubDomains; preload","Vary":"Accept-Encoding","X-Frame-Options":"SAMEORIGIN","x-ms-portal-app":"site-d40aeee5-a782-45ad-8f5a-540d634ba4ad-EUn","x-ms-request-id":"2cbaa6b5-3f17-4597-b884-215ef4467f2c"},"ssl-verify":true,"status":"200"}