{"elapsed":"1.252","endpoint-url":"https://www.epsom-ewell.gov.uk/sites/default/files/BLR%20summary%202019%20csv.csv","entry-date":"2022-07-22T00:22:17.991443","request-headers":{"Accept":"*/*","Accept-Encoding":"gzip, deflate","Connection":"keep-alive","User-Agent":"DLUHC Digital Land"},"response-headers":{"Accept-Ranges":"bytes","Age":"0","Cache-Control":"public, max-age=30","Connection":"keep-alive","Content-Encoding":"gzip","Content-Language":"en","Content-Length":"31625","Content-Type":"text/html; charset=utf-8","Date":"Fri, 22 Jul 2022 00:53:44 GMT","Etag":"W/\"1658451224-0\"","Expires":"Sun, 19 Nov 1978 05:00:00 GMT","Last-Modified":"Fri, 22 Jul 2022 00:53:44 GMT","Link":"<https://www.epsom-ewell.gov.uk/>; rel=\"canonical\",<https://www.epsom-ewell.gov.uk/>; rel=\"shortlink\"","Permissions-Policy":"interest-cohort=()","Server":"nginx","Strict-Transport-Security":"max-age=300","Traceparent":"00-9a3f4f6db9b04de48f37685e4c02c3cf-e26d0f6c4bf0050f-00","Vary":"Accept-Encoding, Cookie, Cookie, Cookie","Via":"1.1 varnish, 1.1 varnish","X-Cache":"MISS, MISS","X-Cache-Hits":"0, 0","X-Cloud-Trace-Context":"9a3f4f6db9b04de48f37685e4c02c3cf/16315713982838080783;o=0","X-Content-Type-Options":"nosniff","X-Drupal-Cache":"MISS","X-Pantheon-Styx-Hostname":"styx-fe1fe2-c-6c94847858-cc9tj","X-Served-By":"cache-ams12738-AMS, cache-bur-kbur8200087-BUR","X-Styx-Req-Id":"bcb8dbb1-0958-11ed-b3bf-4e71440f5486","X-Timer":"S1658451224.268353,VS0,VE683"},"ssl-verify":true,"status":"404"}