{"elapsed":"2.462","endpoint-url":"https://www.salford.gov.uk/media/391607/salford-brownfieldregister-2017-12-01-rev1.csv","entry-date":"2021-12-16T00:28:42.452266","request-headers":{"Accept":"*/*","Accept-Encoding":"gzip, deflate","Connection":"keep-alive","User-Agent":"Digital Land"},"resource":"2a7b9d74419a9388b37862f100293f18ebeee60212d69e9e1f2e1fdb402375f4","response-headers":{"Accept-Ranges":"bytes","Content-Length":"126238","Content-Type":"application/octet-stream","Date":"Thu, 16 Dec 2021 00:39:14 GMT","ETag":"\"9dbcf010846ad31:0\"","Last-Modified":"Fri, 01 Dec 2017 09:09:17 GMT","Set-Cookie":"NSC_ESNS=0bde9e8b-8ab2-11ba-9678-f282fc315f59_2640922128_1801258621_00000000000198180100; Path=/; Expires=Thu, 16-Dec-2021 00:39:29 GMT","Strict-Transport-Security":"max-age=157680000"},"ssl-verify":true,"status":"200"}