{"elapsed":"0.503","endpoint-url":"https://www.broads-authority.gov.uk/brownfield_register","entry-date":"2021-01-19T00:42:27.836060","request-headers":{"Accept":"*/*","Accept-Encoding":"gzip, deflate","Connection":"keep-alive","Cookie":"SQ_SYSTEM_SESSION=mvci4j4qrdk5b0ugnl8gkutk4i8mauc5krlcp384qfta367q6vvpbiq7ijj7giqhsuuvg48c89mdp9a3825qe6rss8rlq90tnoo3rj0","User-Agent":"Digital Land"},"resource":"0934908c6ffa5236cc4bd473d7dc6ce1d8ef8383d9a93e1f594c6af73e6b4954","response-headers":{"Accept-Ranges":"bytes","Cache-Control":"stale-if-error=2592000, max-age=2592000","Connection":"keep-alive","Content-Type":"application/octet-stream","Date":"Tue, 19 Jan 2021 00:54:52 GMT","ETag":"\"5fdb87e7-6d07\"","Expires":"Thu, 18 Feb 2021 00:54:52 GMT","Last-Modified":"Thu, 17 Dec 2020 16:31:35 GMT","Server":"openresty","Transfer-Encoding":"chunked","Via":"1.1 np-web01.ash2.squiz.cloud","X-Cache":"MISS from np-web01.ash2.squiz.cloud","X-Content-Type-Options":"nosniff","X-Request-ID":"c2767d1b-de88-4205-83c5-6ad1fa252f4d"},"ssl-verify":true,"status":"200"}