{"elapsed":"1.011","endpoint-url":"https://liverpool.gov.uk/media/1356598/blr-2020-x-107_mi.csv","entry-date":"2023-03-20T00:19:44.688969","request-headers":{"Accept":"*/*","Accept-Encoding":"gzip, deflate","Connection":"keep-alive","Cookie":".ASPXANONYMOUS=b9vCoGkN2GZMuEOLt80b6nr1WNrHsMjfTjG4JCE2q0yv0xsC4buodH21WRI011Y9YVEO2VCjLcmkxNKfAh47jC-eYJn0rt9oakLzORXvfRyfEDzN7syvfkLeADVzcIFuN3n3zoSOwhHk0IgC-rur6Q2; BIGipServerliverpool.gov.uk-https-test=2977474752.20480.0000","User-Agent":"DLUHC Digital Land"},"response-headers":{"Content-Length":"0","Date":"Mon, 20 Mar 2023 01:17:17 GMT","Referrer-Policy":"no-referrer-when-downgrade","Server":"Microsoft-IIS/10.0"},"ssl-verify":true,"status":"404"}