{"elapsed":"2.165","endpoint-url":"http://datashare.colchester.gov.uk/download/planning-and-licensing/brownfield-land-register/dec-2017/CSV","entry-date":"2022-07-18T00:20:23.658683","request-headers":{"Accept":"*/*","Accept-Encoding":"gzip, deflate","Connection":"keep-alive","Cookie":"Dynamics365PortalAnalytics=dkJfDKPgzLUBI2UxZigRBzc3ZzIPJgv7bBIncFGD2iTmuEcLXPE5BCdnNq3VYSBoVLZbLU3RTkareRTUX1XtgGMRgPQzBMYgpP4xywhdFhiSm_bSxvs0Lk-6zE2rDCtUbZA7x383Po1ts0FwGZ3wLQ2; ARRAffinity=fec40b63f82d12ee43e7f521e2653a2038f56c6e0dec349ab3161dc43551bc77; ARRAffinitySameSite=fec40b63f82d12ee43e7f521e2653a2038f56c6e0dec349ab3161dc43551bc77","User-Agent":"DLUHC Digital Land"},"response-headers":{"Access-Control-Allow-Headers":"https://cbc-live-dotgovresources.azurewebsites.net/*","Access-Control-Allow-Methods":"GET, OPTIONS","Access-Control-Allow-Origin":"https://login.microsoftonline.com","Cache-Control":"no-cache","Content-Encoding":"gzip","Content-Length":"19368","Content-Type":"text/html; charset=utf-8","Date":"Mon, 18 Jul 2022 00:54:39 GMT","Expires":"-1","Pragma":"no-cache","Set-Cookie":"ASP.NET_SessionId=1yvjyaosewpchcsjc2as0yet; path=/; secure; HttpOnly; SameSite=None","Strict-Transport-Security":"max-age=31536000; includeSubDomains; preload","Vary":"Accept-Encoding","X-Frame-Options":"SAMEORIGIN","x-ms-portal-app":"site-d40aeee5-a782-45ad-8f5a-540d634ba4ad-EUn","x-ms-request-id":"b0e0487e-c1da-4697-862e-a50e96794327"},"ssl-verify":true,"status":"200"}