{"elapsed":"0.922","endpoint-url":"https://www.woking2027.info/ldfregisters/brownfieldlandregistercsv.csv","entry-date":"2024-01-18T00:20:54.467549","request-headers":{"Accept":"*/*","Accept-Encoding":"gzip, deflate","Connection":"keep-alive","User-Agent":"DLUHC Digital Land"},"resource":"06f9f968ab778ba1a43f8f147d2f87272df7f3fa109f924d814563c46f207f02","response-headers":{"Accept-Ranges":"bytes","CF-Cache-Status":"EXPIRED","CF-RAY":"8472dce70a289681-SJC","Cache-control":"max-age=14400","Connection":"keep-alive","Content-Length":"29661","Content-Type":"application/octet-stream","Date":"Thu, 18 Jan 2024 00:53:47 GMT","Expires":"Thu, 18 Jan 2024 00:53:47 GMT","Last-Modified":"Wed, 17 Jan 2024 11:34:07 GMT","NEL":"{\"success_fraction\":0,\"report_to\":\"cf-nel\",\"max_age\":604800}","Pragma":"no-cache","Referrer-Policy":"no-referrer-when-downgrade","Report-To":"{\"endpoints\":[{\"url\":\"https:\\/\\/a.nel.cloudflare.com\\/report\\/v3?s=P9rhIPg6%2Fz00IYL0elnAEw3xhr5EnegNk697cvw3zu8iEFgoK5y6NNiVV7D9izX%2BCXY8ZPUhzyxh7Yo%2Bfp6WdLJNQni8yb5RkW80yEp13Tu0WThhaud0CJpeWm7TuxZ5O%2B2Dj773\"}],\"group\":\"cf-nel\",\"max_age\":604800}","Server":"cloudflare","Vary":"Accept-Encoding","X-Content-Type-Options":"nosniff","X-XSS-Protection":"1; mode=block","alt-svc":"h3=\":443\"; ma=86400"},"ssl-verify":true,"status":"200"}