{"elapsed":"1.123","endpoint-url":"https://www.west-lindsey.gov.uk/_resources/assets/attachment/full/0/55646.csv","entry-date":"2022-04-04T00:17:07.790510","request-headers":{"Accept":"*/*","Accept-Encoding":"gzip, deflate","Connection":"keep-alive","User-Agent":"DLUHC Digital Land"},"response-headers":{"Cache-Control":"max-age=1800, public","Connection":"keep-alive","Content-Language":"en","Content-Type":"text/html; charset=UTF-8","Date":"Mon, 04 Apr 2022 00:58:42 GMT","ETag":"\"1649033922\"","Expires":"Sun, 19 Nov 1978 05:00:00 GMT","Last-Modified":"Mon, 04 Apr 2022 00:58:42 GMT","Link":"<https://www.west-lindsey.gov.uk/page-cannot-be-found>; rel=\"canonical\", <https://www.west-lindsey.gov.uk/page-cannot-be-found>; rel=\"canonical\"","Permissions-Policy":"interest-cohort=()","Server":"nginx","Strict-Transport-Security":"max-age=63072000; includeSubdomains; preload","Transfer-Encoding":"chunked","Vary":"Cookie","Via":"1.1 6085ae9abfe185eabb8b69d91c76ba4a.cloudfront.net (CloudFront)","X-Amz-Cf-Id":"MlV5_CdSysOzIiSRu1NC1H_DY45-Xt3JlhGAhrBq2n2deBEN-_Rq3w==","X-Amz-Cf-Pop":"YTO50-C1","X-Cache":"Error from cloudfront","X-Content-Type-Options":"nosniff","X-Drupal-Cache":"MISS","X-Drupal-Dynamic-Cache":"UNCACHEABLE","X-Frame-Options":"SAMEORIGIN","X-XSS-Protection":"1; mode=block"},"ssl-verify":true,"status":"404"}