{"elapsed":"0.705","endpoint-url":"https://northtyneside.objective.co.uk/file/5587332","entry-date":"2023-05-20T00:17:38.511849","request-headers":{"Accept":"*/*","Accept-Encoding":"gzip, deflate","Connection":"keep-alive","User-Agent":"DLUHC Digital Land"},"resource":"33df9ace674c23689ecfd37907e4d9bc1e456185b73a1bb73008249d2c1fc5ee","response-headers":{"Connection":"keep-alive","Content-Length":"25763","Content-Type":"application/octet-stream; charset=UTF-8","Content-disposition":"attachment; filename=\"brownfield-land.csv.csv\"","Date":"Sat, 20 May 2023 00:52:21 GMT","Expires":"Sat, 20 May 2023 00:52:21 GMT","Server":"OCL","Set-Cookie":"AWSALB=7w9ehfMYNyEiHjYM23aXiLT+W0DApTLzpbi31iXuKXtUNw8KUmSPesWPdTNlCCOllMZLLH+0YObFoB3/00HtBVdbTH++2eW7dBYjXgHbrbDFnvBlZze3j2wEqYJa; Expires=Sat, 27 May 2023 00:52:21 GMT; Path=/, AWSALBCORS=7w9ehfMYNyEiHjYM23aXiLT+W0DApTLzpbi31iXuKXtUNw8KUmSPesWPdTNlCCOllMZLLH+0YObFoB3/00HtBVdbTH++2eW7dBYjXgHbrbDFnvBlZze3j2wEqYJa; Expires=Sat, 27 May 2023 00:52:21 GMT; Path=/; SameSite=None; Secure","Strict-Transport-Security":"max-age=63072000; includeSubdomains;","X-Content-Type-Options":"nosniff","X-XSS-Protection":"1; mode=block"},"ssl-verify":true,"status":"200"}