{"elapsed":"0.585","endpoint-url":"https://www.arun.gov.uk/download.cfm?doc=docm93jijm4n18421.csv&ver=19663","entry-date":"2022-10-21T00:25:59.713436","request-headers":{"Accept":"*/*","Accept-Encoding":"gzip, deflate","Connection":"keep-alive","Cookie":"JSESSIONID=88C391AF13980F8EC3B04642528CFF47; TS01c7adea=01667a34effbccb4b8b1f65a08678b3ac1c48330d56ca561f46295cc95c0dca0c79fb26d2a889ddc96099a41049e8bfc77449a7fc4","User-Agent":"DLUHC Digital Land"},"resource":"3c12903110d1db128728a1dbd69069b6345b6db2a15afdb0ae6fc066eecfbcf5","response-headers":{"Connection":"keep-alive","Content-Disposition":"inline; filename=Arun_BrownfieldLandRegister_2021-12-17.csv","Content-Length":"23060","Content-Type":"text/csv","Strict-Transport-Security":"max-age=15768000","X-Responder":"RD3"},"ssl-verify":true,"status":"200"}