{"elapsed":"1.127","endpoint-url":"https://www.dorsetcouncil.gov.uk/planning-buildings-land/planning-policy/brownfield-land-register/brownfield-land.csv","entry-date":"2023-05-13T00:17:45.110039","request-headers":{"Accept":"*/*","Accept-Encoding":"gzip, deflate","Connection":"keep-alive","Cookie":"AWSELB=558D19E11CF2DAF526A74639619D947D45E81727947861F27D6EA146C4AF15F4CE2ACD20E5AD0BB9F855A2263D6E380BCBD04DB2DD9585F26D898B375E6F80AE75C8EAE5A1A4A536C69DBD31C0B964A73EF39880F4; COOKIE_SUPPORT=true; GUEST_LANGUAGE_ID=en_GB; JSESSIONID=C8063B911B0AB6F51111CC9D0615EB7A","User-Agent":"DLUHC Digital Land"},"response-headers":{"Cache-Control":"no-cache, no-store, must-revalidate, private, private, no-cache, no-store, must-revalidate","Connection":"keep-alive","Content-Type":"text/html;charset=UTF-8","Date":"Sat, 13 May 2023 00:56:47 GMT","Expires":"Thu, 01 Jan 1970 00:00:00 GMT","Pragma":"no-cache, no-cache","Referrer-Policy":"strict-origin-when-cross-origin","Server":"Placecube","Strict-Transport-Security":"max-age=31536000; includeSubdomains;","Transfer-Encoding":"chunked","X-Content-Type-Options":"nosniff, nosniff","X-Frame-Options":"SAMEORIGIN, SAMEORIGIN","X-Permitted-Cross-Domain-Policies":"none","X-XSS-Protection":"1"},"ssl-verify":true,"status":"404"}