{"elapsed":"0.299","endpoint-url":"https://drive.google.com/file/d/15sajQfovGJMZdfPVl4q8J3JaT5pKA2MW/view","entry-date":"2021-12-05T00:29:41.785064","request-headers":{"Accept":"*/*","Accept-Encoding":"gzip, deflate","Connection":"keep-alive","Cookie":"NID=511=t_HPA5YiOclBYVMiRF8DDDmSiyTj0Aqa9iAkVdVVMBD_aUiU3qFcE0XeP6qUAaYbFtED_tWHtgYC9oe-LiXzR0uPdPjLjku4yKvbAfg1JXU8NM6pfzrtsWa8txFS-Xgz-u9TuksGkV8LZV_UkgcS06mIh6LWj39HPaJOr2FiynY","User-Agent":"Digital Land"},"response-headers":{"Alt-Svc":"h3=\":443\"; ma=2592000,h3-29=\":443\"; ma=2592000,h3-Q050=\":443\"; ma=2592000,h3-Q046=\":443\"; ma=2592000,h3-Q043=\":443\"; ma=2592000,quic=\":443\"; ma=2592000; v=\"46,43\"","Cache-Control":"no-cache, no-store, max-age=0, must-revalidate","Content-Encoding":"gzip","Content-Security-Policy":"frame-ancestors 'self'","Content-Type":"text/html; charset=utf-8","Date":"Sun, 05 Dec 2021 01:02:45 GMT","Expires":"Mon, 01 Jan 1990 00:00:00 GMT","Pragma":"no-cache","Referrer-Policy":"origin","Server":"GSE","Transfer-Encoding":"chunked","Vary":"Sec-Fetch-Dest, Sec-Fetch-Mode, Sec-Fetch-Site","X-Content-Type-Options":"nosniff","X-Frame-Options":"SAMEORIGIN","X-Robots-Tag":"noindex, nofollow, nosnippet","X-XSS-Protection":"1; mode=block"},"ssl-verify":true,"status":"200"}