{"elapsed":"0.978","endpoint-url":"https://www.sstaffs.gov.uk/doc/180553/name/BrownField%20Register%202019%20CSV.csv/","entry-date":"2023-06-27T00:21:52.334465","request-headers":{"Accept":"*/*","Accept-Encoding":"gzip, deflate","Connection":"keep-alive","User-Agent":"DLUHC Digital Land"},"response-headers":{"Cache-Control":"max-age=1800, public","Connection":"keep-alive","Content-Language":"en","Content-Type":"text/html; charset=UTF-8","Date":"Tue, 27 Jun 2023 01:00:35 GMT","ETag":"\"1687827635\"","Expires":"Sun, 19 Nov 1978 05:00:00 GMT","Last-Modified":"Tue, 27 Jun 2023 01:00:35 GMT","Permissions-Policy":"interest-cohort=()","Server":"nginx","Strict-Transport-Security":"max-age=63072000; includeSubdomains; preload","Transfer-Encoding":"chunked","Vary":"Cookie","Via":"1.1 9861b63db923a2e243e3f4c28421c442.cloudfront.net (CloudFront)","X-Amz-Cf-Id":"nChqajYHecBRIE9zuEqRFEwuoLox2vAB6vUVXXZJLyf9pmvOdhiAAg==","X-Amz-Cf-Pop":"DFW56-P3","X-Cache":"Error from cloudfront","X-Content-Type-Options":"nosniff","X-Drupal-Cache":"MISS","X-Drupal-Dynamic-Cache":"UNCACHEABLE","X-Frame-Options":"SAMEORIGIN","X-XSS-Protection":"1; mode=block"},"ssl-verify":true,"status":"404"}