{"elapsed":"0.599","endpoint-url":"https://bbcdevwebfiles.blob.core.windows.net/webfiles/Planning%20and%20Building/Planning%20Policy/Bedford%20Brownfield%20Register%20Dec%202020%20csv.csv","entry-date":"2022-07-30T00:18:33.385693","request-headers":{"Accept":"*/*","Accept-Encoding":"gzip, deflate","Connection":"keep-alive","User-Agent":"DLUHC Digital Land"},"response-headers":{"Content-Length":"215","Content-Type":"application/xml","Date":"Sat, 30 Jul 2022 01:01:39 GMT","Server":"Windows-Azure-Blob/1.0 Microsoft-HTTPAPI/2.0","Vary":"Origin","x-ms-request-id":"375515fe-901e-008a-56af-a3b99f000000","x-ms-version":"2009-09-19"},"ssl-verify":true,"status":"404"}